rectanglepy/__init__.py
rectanglepy/rectangle.py
rectanglepy/data/hao1_annotations_small.zip
rectanglepy/data/hao1_counts_small.zip
rectanglepy/data/small_fino_bulks.zip
rectanglepy/pp/__init__.py
rectanglepy/pp/create_signature.py
rectanglepy/pp/rectangle_signature.py
rectanglepy/tl/__init__.py
rectanglepy/tl/deconvolution.py
rectanglepy-1.2.0.dist-info/METADATA
rectanglepy-1.2.0.dist-info/WHEEL
rectanglepy-1.2.0.dist-info/licenses/LICENSE
rectanglepy-1.2.0.dist-info/RECORD
