Metadata-Version: 2.4
Name: rectanglepy
Version: 1.2.0
Summary: Hierarchical deconvolution of bulk  transcriptomics
Project-URL: Documentation, https://rectanglepy.readthedocs.io/
Project-URL: Source, https://github.com/ComputationalBiomedicineGroup/Rectangle
Project-URL: Home-page, https://github.com/ComputationalBiomedicineGroup/Rectangle
Author: Bernhard Eder
Maintainer-email: Bernhard Eder <Bernhard.Eder@student.uibk.ac.at>
License:                     GNU AFFERO GENERAL PUBLIC LICENSE
License-File: LICENSE
Requires-Python: >=3.10
Requires-Dist: anndata<0.10.9,>=0.8.0
Requires-Dist: loguru
Requires-Dist: numpy<2.0.0,>=1.0.0
Requires-Dist: osqp>=1.0.5
Requires-Dist: pandas<3.0.0,>=2.0.0
Requires-Dist: pydeseq2==0.4.11
Requires-Dist: scipy==1.13.0
Requires-Dist: setuptools<70.0.0,>=69.0.0
Requires-Dist: statsmodels>=0.14.1
Provides-Extra: dev
Requires-Dist: bump2version; extra == 'dev'
Requires-Dist: pre-commit; extra == 'dev'
Requires-Dist: twine>=4.0.2; extra == 'dev'
Provides-Extra: doc
Requires-Dist: furo; extra == 'doc'
Requires-Dist: ipykernel; extra == 'doc'
Requires-Dist: ipython; extra == 'doc'
Requires-Dist: myst-nb; extra == 'doc'
Requires-Dist: sphinx; extra == 'doc'
Requires-Dist: sphinx-autodoc-typehints; extra == 'doc'
Requires-Dist: sphinx-book-theme; extra == 'doc'
Requires-Dist: sphinx-copybutton; extra == 'doc'
Requires-Dist: sphinxcontrib-bibtex; extra == 'doc'
Provides-Extra: test
Requires-Dist: pytest; extra == 'test'
